apfel-0.0.4.data/scripts/apfel
apfel-0.0.4.data/scripts/apfel-runqemu
apfel-0.0.4.data/scripts/vm_bundle.sh
apfel-0.0.4.data/scripts/vm_create.sh.template
bumper/__init__.py
bumper/__main__.py
apfel-0.0.4.dist-info/LICENSE
apfel-0.0.4.dist-info/METADATA
apfel-0.0.4.dist-info/WHEEL
apfel-0.0.4.dist-info/entry_points.txt
apfel-0.0.4.dist-info/top_level.txt
apfel-0.0.4.dist-info/RECORD
