Metadata-Version: 2.1
Name: apfel
Version: 0.0.4
Summary: Apfel CLI tools
Home-page: https://github.com/avnet-embedded/simplecore-tools
Author: Avnet Embedded GmbH
License: GPL-3.0-only
License-File: LICENSE
Requires-Dist: GitPython (<4.0,>=3.1)
